nkkbmiTest/bmitest.py
nkkbmiTest-0.0.0.2.dist-info/METADATA
nkkbmiTest-0.0.0.2.dist-info/WHEEL
nkkbmiTest-0.0.0.2.dist-info/top_level.txt
nkkbmiTest-0.0.0.2.dist-info/RECORD
