Metadata-Version: 2.1
Name: nkkbmiTest
Version: 0.0.0.2
Summary: My 002 Test package
Home-page: UNKNOWN
Author: nkk
Author-email: llbiss0101@naver.com
License: MIT
Platform: UNKNOWN
Requires-Python: >=3
